multiplier.v
module multiplier (
    input [15:0] a,b,
    output [15:0] p
);
  wire [31:0] temp_product;
   assign temp_product = a * b;
   assign p = temp_product[26:11];
    
endmodule

IIR.v
module IIR (
    input [15:0] x,b0,b1,a1,
    input reset,clk,
    output reg [15:0] y
);
reg [15:0] x1,x2,y1,t1,t2,o1,o2;
wire [15:0] p1,p2,p3;

multiplier m1(b0,t2,p1);
multiplier m2(b1,x1,p2);
multiplier m3(y,a1,p3);
// register r1(o1,clk,reset,t2);
// register r4(t2,clk,reset,y);
// register r2(x,clk,reset,t1);
// register r3(t1,clk,reset,x1);
// assign o1=p1+p2-p3;
always @(posedge clk or negedge reset) begin
    if (!reset) begin
        y<=0;
        x1<=0;
        y1<=0;
        t1<=0;
        t2<=0;
        o1<=0;
    end
    else begin
    o1<=p1+p2;
    y<=o1-p3;
    y1<=y;
    t1<=x;
    t2<=t1;
    x1<=t2;
    end
end
endmodule

proj.v
module proj(
      input [15:0] data_in,b0,b1,b2,a1,a2,a3,
      input reset,clk,
      input [3:0]order,
      output reg [15:0] data_out
);
wire [15:0] out2,out3,out1;
reg r1,r2,r3;
always @(*) begin
    case (order)
        4'd1: begin
            r1=1'b0;
            r2=1'b1;
            r3=1'b1;
            data_out=out1;
        end
        4'd2: begin
            r1=1'b0;
            r2=1'b0;
            r3=1'b1;
            data_out=out2;
        end
        4'd3: begin
            r1=1'b1;
            r2=1'b1;
            r3=1'b1;
            data_out=out3;
        end
        default: begin
            r1 = 4'b0;
            r1 = 4'b0;
            r1 = 4'b0;
            data_out=0;
        end
    endcase
end
IIR i1(data_in,16'b0000100000000000,b0,a1,reset,clk,out1);
IIR i2(out1,16'b0000100000000000,b1,a2,r2,clk,out2);
IIR i3(out2,16'b0000100000000000,b2,a3,r3,clk,out3);
endmodule

tb_proj.v
module proj_tb;

// Inputs
reg [15:0] x, b0, b1, b2,a1,a2,a3;
reg reset, clk;
reg [3:0] order;

// Outputs
wire [15:0] y;

// Instantiate the Unit Under Test (UUT)
proj uut (
    .data_in(x),
    .b0(b0),
    .b1(b1),
    .b2(b2),
    .a1(a1),
    .a2(a1),
    .a3(a2),
    .reset(reset),
    .clk(clk),
    .order(order),
    .data_out(y)
);
// Read input values from file
    integer file_handle,file_output;
    reg [15:0] input_value;
    integer scan_file;
// Clock generation
initial clk = 0;
always #5 clk = ~clk;
    
initial begin
    $dumpfile("waveform.vcd");
    $dumpvars(0, proj_tb);
    b0 =16'b0000011000001010;
    b1 =16'b0000011000001010;
    b2 =16'b0000011000001010;
    a1 =16'b0000011000001010;
    a2 =16'b0000010000010100;
    a3 =16'b0000010000010100;
    
        // Open the input file
    file_handle = $fopen("wave.txt", "r");
    file_output = $fopen("output.txt", "w");
        
        // Reset the DUT
        reset = 1;
        x=0;
        #10 reset = 0;
        #10 reset = 1;
        // Read input values from file and apply them to the DUT
        while (!$feof(file_handle)) begin
            scan_file = $fscanf(file_handle, "%b", input_value);
            if (scan_file == 1) begin
                #20; // Wait for 5 time units
                x = input_value;
                $fdisplay (file_output,"%b",y);
                
            end
        end       
        // Close the input file
        $fclose(file_handle);       
        // Wait for some time and finish the simulation
        #100 $finish;
    end
  

endmodule

iir_tb.v
module iir_tb;
    reg [15:0] x,b0,b1,a1;
    reg rst, clk;
    wire [15:0] y;
    
    IIR i1(x ,b0,b1,a1, rst, clk, y);
    
    // Clock generation
    initial clk = 0;
    always #10 clk = ~clk;
    
    // Read input values from file
    integer file_handle,file_output;
    reg [15:0] input_value;
    integer scan_file;
    
initial begin
    b0 =16'b0000011000001010;
    b1 =16'b0000011000001010;
    a1 =16'b0000010000010100;
        $dumpfile("waveform.vcd");
    $dumpvars(0, iir_tb);
        // Open the input file
        file_handle = $fopen("wave.txt", "r");
        file_output = $fopen("output.txt", "w");
        
        // Reset the DUT
        rst = 1;
        x=0;
        #10 rst = 0;
        #10 rst = 1;
        // Read input values from file and apply them to the DUT
        while (!$feof(file_handle)) begin
            scan_file = $fscanf(file_handle, "%b", input_value);
            if (scan_file == 1) begin
                #20; // Wait for 5 time units
                x = input_value;
                $fdisplay (file_output,"%b",y);
                
            end
        end
        
        // Close the input file
        $fclose(file_handle);
        
        // Wait for some time and finish the simulation
        #100 $finish;
    end
    
endmodule

waveform.vcd
$date
	Mon May 13 23:04:16 2024
$end
$version
	Icarus Verilog
$end
$timescale
	1s
$end
$scope module iir_tb $end
$var wire 16 ! y [15:0] $end
$var reg 16 " a1 [15:0] $end
$var reg 16 # b0 [15:0] $end
$var reg 16 $ b1 [15:0] $end
$var reg 1 % clk $end
$var reg 16 & input_value [15:0] $end
$var reg 1 ' rst $end
$var reg 16 ( x [15:0] $end
$var integer 32 ) file_handle [31:0] $end
$var integer 32 * file_output [31:0] $end
$var integer 32 + scan_file [31:0] $end
$scope module i1 $end
$var wire 16 , a1 [15:0] $end
$var wire 16 - b0 [15:0] $end
$var wire 16 . b1 [15:0] $end
$var wire 1 % clk $end
$var wire 1 ' reset $end
$var wire 16 / x [15:0] $end
$var wire 16 0 p3 [15:0] $end
$var wire 16 1 p2 [15:0] $end
$var wire 16 2 p1 [15:0] $end
$var reg 16 3 o1 [15:0] $end
$var reg 16 4 t1 [15:0] $end
$var reg 16 5 t2 [15:0] $end
$var reg 16 6 x1 [15:0] $end
$var reg 16 7 y [15:0] $end
$var reg 16 8 y1 [15:0] $end
$scope module m1 $end
$var wire 16 9 a [15:0] $end
$var wire 16 : b [15:0] $end
$var wire 32 ; temp_product [31:0] $end
$var wire 16 < p [15:0] $end
$upscope $end
$scope module m2 $end
$var wire 16 = a [15:0] $end
$var wire 16 > b [15:0] $end
$var wire 32 ? temp_product [31:0] $end
$var wire 16 @ p [15:0] $end
$upscope $end
$scope module m3 $end
$var wire 16 A a [15:0] $end
$var wire 16 B b [15:0] $end
$var wire 32 C temp_product [31:0] $end
$var wire 16 D p [15:0] $end
$upscope $end
$upscope $end
$upscope $end
$scope module proj_tb $end
$var wire 16 E y [15:0] $end
$var reg 16 F a1 [15:0] $end
$var reg 16 G a2 [15:0] $end
$var reg 16 H a3 [15:0] $end
$var reg 16 I b0 [15:0] $end
$var reg 16 J b1 [15:0] $end
$var reg 16 K b2 [15:0] $end
$var reg 1 L clk $end
$var reg 16 M input_value [15:0] $end
$var reg 4 N order [3:0] $end
$var reg 1 O reset $end
$var reg 16 P x [15:0] $end
$var integer 32 Q file_handle [31:0] $end
$var integer 32 R file_output [31:0] $end
$var integer 32 S scan_file [31:0] $end
$scope module uut $end
$var wire 16 T a1 [15:0] $end
$var wire 16 U a2 [15:0] $end
$var wire 16 V a3 [15:0] $end
$var wire 16 W b0 [15:0] $end
$var wire 16 X b1 [15:0] $end
$var wire 16 Y b2 [15:0] $end
$var wire 1 L clk $end
$var wire 16 Z data_in [15:0] $end
$var wire 4 [ order [3:0] $end
$var wire 1 O reset $end
$var wire 16 \ out3 [15:0] $end
$var wire 16 ] out2 [15:0] $end
$var wire 16 ^ out1 [15:0] $end
$var reg 16 _ data_out [15:0] $end
$var reg 1 ` r1 $end
$var reg 1 a r2 $end
$var reg 1 b r3 $end
$scope module i1 $end
$var wire 16 c a1 [15:0] $end
$var wire 16 d b0 [15:0] $end
$var wire 16 e b1 [15:0] $end
$var wire 1 L clk $end
$var wire 1 O reset $end
$var wire 16 f x [15:0] $end
$var wire 16 g p3 [15:0] $end
$var wire 16 h p2 [15:0] $end
$var wire 16 i p1 [15:0] $end
$var reg 16 j o1 [15:0] $end
$var reg 16 k t1 [15:0] $end
$var reg 16 l t2 [15:0] $end
$var reg 16 m x1 [15:0] $end
$var reg 16 n y [15:0] $end
$var reg 16 o y1 [15:0] $end
$scope module m1 $end
$var wire 16 p a [15:0] $end
$var wire 16 q b [15:0] $end
$var wire 32 r temp_product [31:0] $end
$var wire 16 s p [15:0] $end
$upscope $end
$scope module m2 $end
$var wire 16 t a [15:0] $end
$var wire 16 u b [15:0] $end
$var wire 32 v temp_product [31:0] $end
$var wire 16 w p [15:0] $end
$upscope $end
$scope module m3 $end
$var wire 16 x a [15:0] $end
$var wire 16 y b [15:0] $end
$var wire 32 z temp_product [31:0] $end
$var wire 16 { p [15:0] $end
$upscope $end
$upscope $end
$scope module i2 $end
$var wire 16 | a1 [15:0] $end
$var wire 16 } b0 [15:0] $end
$var wire 16 ~ b1 [15:0] $end
$var wire 1 L clk $end
$var wire 1 a reset $end
$var wire 16 !" x [15:0] $end
$var wire 16 "" p3 [15:0] $end
$var wire 16 #" p2 [15:0] $end
$var wire 16 $" p1 [15:0] $end
$var reg 16 %" o1 [15:0] $end
$var reg 16 &" t1 [15:0] $end
$var reg 16 '" t2 [15:0] $end
$var reg 16 (" x1 [15:0] $end
$var reg 16 )" y [15:0] $end
$var reg 16 *" y1 [15:0] $end
$scope module m1 $end
$var wire 16 +" a [15:0] $end
$var wire 16 ," b [15:0] $end
$var wire 32 -" temp_product [31:0] $end
$var wire 16 ." p [15:0] $end
$upscope $end
$scope module m2 $end
$var wire 16 /" a [15:0] $end
$var wire 16 0" b [15:0] $end
$var wire 32 1" temp_product [31:0] $end
$var wire 16 2" p [15:0] $end
$upscope $end
$scope module m3 $end
$var wire 16 3" a [15:0] $end
$var wire 16 4" b [15:0] $end
$var wire 32 5" temp_product [31:0] $end
$var wire 16 6" p [15:0] $end
$upscope $end
$upscope $end
$scope module i3 $end
$var wire 16 7" a1 [15:0] $end
$var wire 16 8" b0 [15:0] $end
$var wire 16 9" b1 [15:0] $end
$var wire 1 L clk $end
$var wire 1 b reset $end
$var wire 16 :" x [15:0] $end
$var wire 16 ;" p3 [15:0] $end
$var wire 16 <" p2 [15:0] $end
$var wire 16 =" p1 [15:0] $end
$var reg 16 >" o1 [15:0] $end
$var reg 16 ?" t1 [15:0] $end
$var reg 16 @" t2 [15:0] $end
$var reg 16 A" x1 [15:0] $end
$var reg 16 B" y [15:0] $end
$var reg 16 C" y1 [15:0] $end
$scope module m1 $end
$var wire 16 D" a [15:0] $end
$var wire 16 E" b [15:0] $end
$var wire 32 F" temp_product [31:0] $end
$var wire 16 G" p [15:0] $end
$upscope $end
$scope module m2 $end
$var wire 16 H" a [15:0] $end
$var wire 16 I" b [15:0] $end
$var wire 32 J" temp_product [31:0] $end
$var wire 16 K" p [15:0] $end
$upscope $end
$scope module m3 $end
$var wire 16 L" a [15:0] $end
$var wire 16 M" b [15:0] $end
$var wire 32 N" temp_product [31:0] $end
$var wire 16 O" p [15:0] $end
$upscope $end
$upscope $end
$upscope $end
$upscope $end
$enddefinitions $end
$comment Show the parameter values. $end
$dumpall
$end
#0
$dumpvars
bx O"
bx N"
b10000010100 M"
bx L"
bx K"
bx J"
bx I"
b11000001010 H"
bx G"
bx F"
bx E"
b100000000000 D"
bx C"
bx B"
bx A"
bx @"
bx ?"
bx >"
bx ="
bx <"
bx ;"
bx :"
b11000001010 9"
b100000000000 8"
b10000010100 7"
bx 6"
bx 5"
b11000001010 4"
bx 3"
bx 2"
bx 1"
bx 0"
b11000001010 /"
bx ."
bx -"
bx ,"
b100000000000 +"
bx *"
bx )"
bx ("
bx '"
bx &"
bx %"
bx $"
bx #"
bx ""
bx !"
b11000001010 ~
b100000000000 }
b11000001010 |
bx {
bx z
b11000001010 y
bx x
bx w
bx v
bx u
b11000001010 t
bx s
bx r
bx q
b100000000000 p
bx o
bx n
bx m
bx l
bx k
bx j
bx i
bx h
bx g
b0 f
b11000001010 e
b100000000000 d
b11000001010 c
xb
xa
x`
bx _
bx ^
bx ]
bx \
bx [
b0 Z
b11000001010 Y
b11000001010 X
b11000001010 W
b10000010100 V
b11000001010 U
b11000001010 T
bx S
b10000000000000000000000000000110 R
b10000000000000000000000000000101 Q
b0 P
1O
bx N
bx M
0L
b11000001010 K
b11000001010 J
b11000001010 I
b10000010100 H
b10000010100 G
b11000001010 F
bx E
bx D
bx C
b10000010100 B
bx A
bx @
bx ?
bx >
b11000001010 =
bx <
bx ;
bx :
b11000001010 9
bx 8
bx 7
bx 6
bx 5
bx 4
bx 3
bx 2
bx 1
bx 0
b0 /
b11000001010 .
b11000001010 -
b10000010100 ,
bx +
b10000000000000000000000000000100 *
b10000000000000000000000000000011 )
b0 (
1'
bx &
0%
b11000001010 $
b11000001010 #
b10000010100 "
bx !
$end
#5
b0 k
1L
#10
b0 i
b0 s
b0 h
b0 w
b0 g
b0 {
b0 E
b0 _
0`
b0 2
b0 <
b0 1
b0 @
b0 0
b0 D
b0 j
b0 r
b0 l
b0 q
b0 o
b0 v
b0 m
b0 u
b0 z
b0 ^
b0 n
b0 x
b0 !"
b0 3
b0 ;
b0 5
b0 :
b0 4
b0 8
b0 ?
b0 6
b0 >
b0 C
b0 !
b0 7
b0 A
0L
0O
0'
1%
#15
b0 &"
1L
#20
0L
b1 S
b10000000000000 M
1O
b1 +
b10000000000000 &
1'
0%
#25
b0 $"
b0 ."
b0 -"
b0 '"
b0 ,"
1L
#30
0L
1%
#35
b0 #"
b0 2"
b0 1"
b0 ("
b0 0"
1L
#40
0L
0%
b1111000010101 M
b10000000000000 P
b10000000000000 Z
b10000000000000 f
b1111000010101 &
b10000000000000 (
b10000000000000 /
#45
b10000000000000 k
b0 %"
1L
#50
b10000000000000 4
0L
1%
#55
b10000000000000 i
b10000000000000 s
b1000000000000000000000000 r
b10000000000000 l
b10000000000000 q
1L
#60
0L
0%
b1100011110010 M
b1111000010101 P
b1111000010101 Z
b1111000010101 f
b1100011110010 &
b1111000010101 (
b1111000010101 /
#65
b1100000101000 h
b1100000101000 w
b110000010100000000000000 v
b10000000000000 m
b10000000000000 u
b1111000010101 k
b10000000000000 j
1L
#70
b1100000101000 2
b1100000101000 <
b110000010100000000000000 ;
b10000000000000 5
b10000000000000 :
b1111000010101 4
0L
1%
#75
b1111000010101 i
b1111000010101 s
b1100000101000 g
b1100000101000 {
b111100001010100000000000 r
b1111000010101 l
b1111000010101 q
b110000010100000000000000 z
b10000000000000 ^
b10000000000000 n
b10000000000000 x
b10000000000000 !"
b11100000101000 j
1L
#80
0L
0%
b1001000111011 M
b1100011110010 P
b1100011110010 Z
b1100011110010 f
b1001000111011 &
b1100011110010 (
b1100011110010 /
#85
b1011010110101 h
b1011010110101 w
b101101011010101011010010 v
b1111000010101 m
b1111000010101 u
b1100011110010 k
b10000000000000 o
b11011000111101 j
b10000000000000 &"
1L
#90
b1100000101000 1
b1100000101000 @
b1011010110101 2
b1011010110101 <
b110000010100000000000000 ?
b10000000000000 6
b10000000000000 >
b101101011010101011010010 ;
b1111000010101 5
b1111000010101 :
b1100011110010 4
b1100000101000 3
0L
1%
#95
b1100011110010 i
b1100011110010 s
b1011010110101 g
b1011010110101 {
b10000000000000 $"
b10000000000000 ."
b110001111001000000000000 r
b1100011110010 l
b1100011110010 q
b101101011010101011010010 z
b1111000010101 ^
b1111000010101 n
b1111000010101 x
b1111000010101 !"
b11010011001010 j
b1000000000000000000000000 -"
b10000000000000 '"
b10000000000000 ,"
1L
#100
0L
0%
b110000000000 M
b1001000111011 P
b1001000111011 Z
b1001000111011 f
b110000000000 &
b1001000111011 (
b1001000111011 /
#105
b1001011010100 h
b1001011010100 w
b1100000101000 #"
b1100000101000 2"
b100101101010010101110100 v
b1100011110010 m
b1100011110010 u
b1001000111011 k
b1111000010101 o
b10111110100111 j
b110000010100000000000000 1"
b10000000000000 ("
b10000000000000 0"
b1111000010101 &"
b10000000000000 %"
1L
#110
b1011010110101 1
b1011010110101 @
b1001011010100 2
b1001011010100 <
b110001010000 0
b110001010000 D
b101101011010101011010010 ?
b1111000010101 6
b1111000010101 >
b100101101010010101110100 ;
b1100011110010 5
b1100011110010 :
b1001000111011 4
b11000101000001100100000 C
b1100000101000 !
b1100000101000 7
b1100000101000 A
b10111011011101 3
0L
1%
#115
b1001000111011 i
b1001000111011 s
b1001011010100 g
b1001011010100 {
b1111000010101 $"
b1111000010101 ."
b100100011101100000000000 r
b1001000111011 l
b1001000111011 q
b100101101010010101110100 z
b1100011110010 ^
b1100011110010 n
b1100011110010 x
b1100011110010 !"
b10101111000110 j
b111100001010100000000000 -"
b1111000010101 '"
b1111000010101 ,"
b11100000101000 %"
1L
#120
0L
0%
b0 S
b110000000000 P
b110000000000 Z
b110000000000 f
b0 +
b110000000000 (
b110000000000 /
#125
b110111000011 h
b110111000011 w
b1011010110101 #"
b1011010110101 2"
b11011100001100001001110 v
b1001000111011 m
b1001000111011 u
b110000000000 k
b1100011110010 o
b10010100001111 j
b101101011010101011010010 1"
b1111000010101 ("
b1111000010101 0"
b1100011110010 &"
b11011000111101 %"
1L
#130
b1001011010100 1
b1001011010100 @
b110111000011 2
b110111000011 <
b1000110011100 0
b1000110011100 D
b100101101010010101110100 ?
b1100011110010 6
b1100011110010 >
b11011100001100001001110 ;
b1001000111011 5
b1001000111011 :
b110000000000 4
b1100000101000 8
b100011001110011100000100 C
b10001010001101 !
b10001010001101 7
b10001010001101 A
b10100110001001 3
0L
1%
#135
b110000000000 i
b110000000000 s
b110111000011 g
b110111000011 {
b1100011110010 $"
b1100011110010 ."
b11000000000000000000000 r
b110000000000 l
b110000000000 q
b11011100001100001001110 z
b1001000111011 ^
b1001000111011 n
b1001000111011 x
b1001000111011 !"
b1111111111110 j
b110001111001000000000000 -"
b1100011110010 '"
b1100011110010 ,"
b11010011001010 %"
1L
#140
0L
0%
#145
b100100001111 h
b100100001111 w
b1001011010100 #"
b1001011010100 2"
b10010000111100000000000 v
b110000000000 m
b110000000000 u
b1001000111011 o
b1100111000011 j
b100101101010010101110100 1"
b1100011110010 ("
b1100011110010 0"
b1001000111011 &"
b10111110100111 %"
1L
#150
b110111000011 1
b110111000011 @
b100100001111 2
b100100001111 <
b110000110010 0
b110000110010 D
b11011100001100001001110 ?
b1001000111011 6
b1001000111011 >
b10010000111100000000000 ;
b110000000000 5
b110000000000 :
b10001010001101 8
b11000011001001010000100 C
b1011111101101 !
b1011111101101 7
b1011111101101 A
b10000010010111 3
0L
1%
#155
b100100001111 g
b100100001111 {
b1001000111011 $"
b1001000111011 ."
b10010000111100000000000 z
b110000000000 ^
b110000000000 n
b110000000000 x
b110000000000 !"
b1010100001111 j
b100100011101100000000000 -"
b1001000111011 '"
b1001000111011 ,"
b10101111000110 %"
1L
#160
0L
0%
#165
b110111000011 #"
b110111000011 2"
b110000000000 o
b11011100001100001001110 1"
b1001000111011 ("
b1001000111011 0"
b110000000000 &"
b10010100001111 %"
1L
#170
b100100001111 1
b100100001111 @
b101001100101 0
b101001100101 D
b10010000111100000000000 ?
b110000000000 6
b110000000000 >
b1011111101101 8
b10100110010101111100100 C
b1010001100101 !
b1010001100101 7
b1010001100101 A
b1011011010010 3
0L
1%
#175
b110000000000 $"
b110000000000 ."
b11000000000000000000000 -"
b110000000000 '"
b110000000000 ,"
b1111111111110 %"
1L
#180
0L
0%
#185
b100100001111 #"
b100100001111 2"
b10010000111100000000000 1"
b110000000000 ("
b110000000000 0"
b1100111000011 %"
1L
#190
b11001010101 0
b11001010101 D
b1010001100101 8
b1100101010110010000100 C
b110001101101 !
b110001101101 7
b110001101101 A
b1001000011110 3
0L
1%
#195
b1010100001111 %"
1L
#200
0L
0%
#205
1L
#210
b11000000001 0
b11000000001 D
b110001101101 8
b1100000000111110110100 C
b101111001001 !
b101111001001 7
b101111001001 A
0L
1%
