proj.v
module proj(
      input [15:0] address,
      input [15:0] data_in,
      input write_enable, input reset, input clk,
      output [15:0] data_out
);
wire [15:0] coeff_x0 =16'b0000100000000000; wire [15:0] coeff_x1=16'b0001000000000000; wire [15:0] coeff_x2=16'b0001100000000000; wire [15:0] coeff_x3=16'b0010000000000000; wire [15:0] coeff_x4=16'b0010100000000000;
     wire [15:0] coeff_x5=16'b0011000000000000;wire [15:0] coeff_y1=16'b0011100000000000; wire [15:0] coeff_y2=16'b0100000000000000; wire [15:0] coeff_y3=16'b0100000000000000;
parameter [3:0] order=4'b0011;
reg [15:0] ram [0:255];wire [12:0] delay_1y;wire [12:0] delay_2y;//wire [12:0] delay_3y;
/*reg signed [12:0] delay_4y;reg signed [12:0] delay_5y;reg signed [12:0] delay_6y;reg signed [12:0] delay_7y;reg signed [12:0] delay_8y;
reg signed [12:0] delay_9y;reg signed [12:0] delay_10y;reg signed [12:0] delay_11y;reg signed [12:0] delay_12y;reg signed [12:0] delay_13y;
reg signed [12:0] delay_14y;*/
always @(posedge clk,negedge reset) begin
    if (!reset) begin 
	    ram[0] <= 16'd0;
        ram[1] <= 16'd0;
        ram[2] <= 16'd0;
        ram[3] <= 16'd0; 
        ram[4] <= 16'd0;
        ram[5] <= 16'd0;
        ram[6] <= 16'd0;
        ram[7] <= 16'd0;
        ram[8] <= 16'd0;
        ram[9] <= 16'd0;
        ram[10] <= 16'd0;
        ram[11] <= 16'd0;
        ram[12] <= 16'd0;
        ram[13] <= 16'd0;
        ram[14] <= 16'd0;
        ram[15] <= 16'd0;
        ram[16] <= 16'd0;
        ram[17] <= 16'd0;
        ram[18] <= 16'd0;
        ram[19] <= 16'd0;
        ram[20] <= 16'd0;
        ram[21] <= 16'd0;
        ram[22] <= 16'd0;
        ram[23] <= 16'd0;
        ram[24] <= 16'd0;
        ram[25] <= 16'd0;
        ram[26] <= 16'd0;
        ram[27] <= 16'd0;
        ram[28] <= 16'd0;
        ram[29] <= 16'd0;
    end
    else if (write_enable) begin
        
        ram[0] <= coeff_x0;
        ram[1] <= coeff_x1;
        ram[2] <= coeff_x2;
        ram[3] <= coeff_x3; 
        ram[4] <= coeff_x4;
        ram[5] <= coeff_x5;
        /*ram[6] <= coeff_x6;
        ram[7] <= coeff_x7;
        ram[8] <= coeff_x8;
        ram[9] <= coeff_x9;
        ram[10] <= coeff_x10;
        ram[11] <= coeff_x11;
        ram[12] <= coeff_x12;
        ram[13] <= coeff_x13;
        ram[14] <= coeff_x14;*/
        ram[15] <= coeff_y1;
        ram[16] <= coeff_y2;
        ram[17] <= coeff_y3;
        /*ram[18] <= coeff_y4;
        ram[19] <= coeff_y5;
        ram[20] <= coeff_y6;
        ram[21] <= coeff_y7;
        ram[22] <= coeff_y8;
        ram[23] <= coeff_y9;
        ram[24] <= coeff_y10;
        ram[25] <= coeff_y11;
        ram[26] <= coeff_y12;
        ram[27] <= coeff_y13;
        ram[28] <= coeff_y14;*/
        ram[29] <= data_out;
   
    end 
    end
        generate
        if (order == 4'b0011) begin
            IIR r1(
                .x(data_in),
                .reset(reset),
                .clk(clk),
                .a0(ram[0]),
                .a1(ram[1]),
                .b1(ram[15]),
                .y(data_out)
            );
            IIR r2(
                .x(data_out),
                .reset(reset),
                .clk(clk),
                .a0(ram[2]),
                .a1(ram[3]),
                .b1(ram[16]),
                .y(delay_1y)
            );
            IIR r3(
                .x(delay_1y),
                .reset(reset),
                .clk(clk),
                .a0(ram[4]),
                .a1(ram[5]),
                .b1(ram[17]),
                .y(delay_2y)
            );
        end
        
    endgenerate
	 endmodule
	 
	 module IIR (
    input [15:0] x,
    input reset,clk,
    input wire [15:0] a0,a1,b1,
    output  [15:0] y
);
reg [15:0] x1,x2,y1,t1;
wire [15:0] p1,p2,p3;
//parameter
//a0 =16'b1111100111110110,
//a1 =16'b0000010000010100,
//b1 =16'b0000011000001010;
multiplier m1(b1,x,p1);
multiplier m2(a1,x1,p2);
multiplier m3(y1,b1,p3);
   assign y=p1+p2-p3;
always @(posedge clk or negedge reset) begin
    if (!reset) begin
        x1<=0;
        y1<=0; 
        t1<=0; 
    end
    else begin 
    t1<=x;
    x1<=t1;
    y1<=y;

    end
end
endmodule

module multiplier (
    input [15:0] a,b,
    output [15:0] p
);
  wire [31:0] temp_product;
   assign temp_product = a * b;
   assign p = temp_product[26:11];
    
endmodule

test1.v
module test1 ();
  reg [15:0] a, b;
  wire [15:0]  d;
  multiplier m1(a, b, d);

  initial begin
    $dumpfile("waveform.vcd");
    $dumpvars(0, test1);
    a = 16'b0_0011_11000000000;
    b = 16'b0_0100_10000000000; // Assigning a value to 'b' for completeness
    #10; // Delay added to allow simulation to advance
    $display("c = %d.%d", d[14:11],d[10:0]); // Displaying 'c' in binary format
  end
endmodule

iir_tb.v
module iir_tb;
    reg [15:0] x;
    reg rst, clk;
    wire [15:0] y;
    
    IIR i1(x, rst, clk, y);
    
    // Clock generation
    initial clk = 0;
    always #10 clk = ~clk;
    
    // Read input values from file
    integer file_handle,file_output;
    reg [15:0] input_value;
    integer scan_file;
    
    initial begin
        $dumpfile("waveform.vcd");
    $dumpvars(0, iir_tb);
        // Open the input file
        file_handle = $fopen("wave.txt", "r");
        file_output = $fopen("output.txt", "w");
        
        // Reset the DUT
        rst = 1;
        x=0;
        #10 rst = 0;
        #10 rst = 1;
        // Read input values from file and apply them to the DUT
        while (!$feof(file_handle)) begin
            scan_file = $fscanf(file_handle, "%b", input_value);
            if (scan_file == 1) begin
                #20; // Wait for 5 time units
                x = input_value;
                $fdisplay (file_output,"%b",y);
                
            end
        end
        
        // Close the input file
        $fclose(file_handle);
        
        // Wait for some time and finish the simulation
        #100 $finish;
    end
    
endmodule

waveform.vcd
$date
	Sun May 12 14:01:12 2024
$end
$version
	Icarus Verilog
$end
$timescale
	1s
$end
$scope module iir_tb $end
$var wire 16 ! y [15:0] $end
$var reg 1 " clk $end
$var reg 16 # input_value [15:0] $end
$var reg 1 $ rst $end
$var reg 16 % x [15:0] $end
$var integer 32 & file_handle [31:0] $end
$var integer 32 ' file_output [31:0] $end
$var integer 32 ( scan_file [31:0] $end
$scope module i1 $end
$var wire 1 " clk $end
$var wire 1 $ reset $end
$var wire 16 ) x [15:0] $end
$var wire 16 * y [15:0] $end
$var wire 16 + p3 [15:0] $end
$var wire 16 , p2 [15:0] $end
$var wire 16 - p1 [15:0] $end
$var parameter 16 . a0 $end
$var parameter 16 / a1 $end
$var parameter 16 0 b1 $end
$var reg 16 1 t1 [15:0] $end
$var reg 16 2 x1 [15:0] $end
$var reg 16 3 y1 [15:0] $end
$scope module m1 $end
$var wire 16 4 a [15:0] $end
$var wire 16 5 b [15:0] $end
$var wire 32 6 temp_product [31:0] $end
$var wire 16 7 p [15:0] $end
$upscope $end
$scope module m2 $end
$var wire 16 8 a [15:0] $end
$var wire 16 9 b [15:0] $end
$var wire 32 : temp_product [31:0] $end
$var wire 16 ; p [15:0] $end
$upscope $end
$scope module m3 $end
$var wire 16 < a [15:0] $end
$var wire 16 = b [15:0] $end
$var wire 32 > temp_product [31:0] $end
$var wire 16 ? p [15:0] $end
$upscope $end
$upscope $end
$upscope $end
$scope module test1 $end
$var wire 16 @ d [15:0] $end
$var reg 16 A a [15:0] $end
$var reg 16 B b [15:0] $end
$scope module m1 $end
$var wire 16 C a [15:0] $end
$var wire 16 D b [15:0] $end
$var wire 32 E temp_product [31:0] $end
$var wire 16 F p [15:0] $end
$upscope $end
$upscope $end
$enddefinitions $end
$comment Show the parameter values. $end
$dumpall
b11000001010 0
b10000010100 /
b1111100111110110 .
$end
#0
$dumpvars
b1000011100000000 F
b100001110000000000000000000 E
b10010000000000 D
b1111000000000 C
b10010000000000 B
b1111000000000 A
b1000011100000000 @
b0 ?
b0 >
b11000001010 =
b0 <
b0 ;
b0 :
b0 9
b10000010100 8
b0 7
b0 6
b0 5
b11000001010 4
b0 3
b0 2
b0 1
b0 -
b0 ,
b0 +
b0 *
b0 )
bx (
b10000000000000000000000000000100 '
b10000000000000000000000000000011 &
b0 %
0$
bx #
0"
b0 !
$end
#10
b10000000000000 1
b1100000101000 !
b1100000101000 *
b1100000101000 -
b1100000101000 7
b110000010100000000000000 6
b10000000000000 %
b10000000000000 )
b10000000000000 5
b1 (
b10000000000000 #
1$
1"
#20
0"
#30
b10010001111 +
b10010001111 ?
b1000001010000 ,
b1000001010000 ;
b1001000111100001100100 >
b11000001010 3
b11000001010 <
b100000101000000000000000 :
b10000000000000 2
b10000000000000 9
b100000000000 1
b1000111001011 !
b1000111001011 *
b11000001010 -
b11000001010 7
1"
b1100000101000000000000 6
b100000000000 %
b100000000000 )
b100000000000 5
b100000000000 #
#40
0"
#50
b1000111111101 +
b1000111111101 ?
b10000010100 ,
b10000010100 ;
b100011111110110001010010 >
b1011111010101 3
b1011111010101 <
b1000001010000000000000 :
b100000000000 2
b100000000000 9
b1000000000000 1
b1111111000101011 !
b1111111000101011 *
b110000010100 -
b110000010100 7
1"
b11000001010000000000000 6
b1000000000000 %
b1000000000000 )
b1000000000000 5
b1000000000000 #
#60
0"
#70
b1011101101001110 +
b1011101101001110 ?
b100000101000 ,
b100000101000 ;
b101110110100111011101001010 >
b1111100000100001 3
b1111100000100001 <
b10000010100000000000000 :
b1000000000000 2
b1000000000000 9
b100000000000 1
b101001011100100 !
b101001011100100 *
b11000001010 -
b11000001010 7
1"
b1100000101000000000000 6
b100000000000 %
b100000000000 )
b100000000000 5
b100000000000 #
#80
0"
#90
b100110000111111 +
b100110000111111 ?
b10000010100 ,
b10000010100 ;
b10011000011111111000010100 >
b110010100000010 3
b110010100000010 <
b1000001010000000000000 :
b100000000000 2
b100000000000 9
b10000000000000 1
b1100111111111101 !
b1100111111111101 *
b1100000101000 -
b1100000101000 7
1"
b110000010100000000000000 6
b10000000000000 %
b10000000000000 )
b10000000000000 5
b10000000000000 #
#100
0"
#110
b1000111101010100 +
b1000111101010100 ?
b1000001010000 ,
b1000001010000 ;
b100011110101010010010110110 >
b1011110111011111 3
b1011110111011111 <
b100000101000000000000000 :
b10000000000000 2
b10000000000000 9
b100000000000 1
b1000011100000110 !
b1000011100000110 *
b11000001010 -
b11000001010 7
1"
b1100000101000000000000 6
b100000000000 %
b100000000000 )
b100000000000 5
b100000000000 #
#120
0"
#130
b110101001111100 +
b110101001111100 ?
b10000010100 ,
b10000010100 ;
b11010100111110001010100000 >
b1000110100010000 3
b1000110100010000 <
b1000001010000000000000 :
b100000000000 2
b100000000000 9
b1000000000000 1
b1010010110101100 !
b1010010110101100 *
b110000010100 -
b110000010100 7
1"
b11000001010000000000000 6
b1000000000000 %
b1000000000000 )
b1000000000000 5
b1000000000000 #
#140
0"
#150
b111100010000001 +
b111100010000001 ?
b100000101000 ,
b100000101000 ;
b11110001000000100001010100 >
b1001111110100010 3
b1001111110100010 <
b10000010100000000000000 :
b1000000000000 2
b1000000000000 9
b100000000000 1
b1001010110110001 !
b1001010110110001 *
b11000001010 -
b11000001010 7
1"
b1100000101000000000000 6
b100000000000 %
b100000000000 )
b100000000000 5
b100000000000 #
#160
0"
#170
b111111010101101 +
b111111010101101 ?
b10000010100 ,
b10000010100 ;
b11111101010110100000010110 >
b1010011111001111 3
b1010011111001111 <
b1000001010000000000000 :
b100000000000 2
b100000000000 9
b10000000000000 1
b1001110110001111 !
b1001110110001111 *
b1100000101000 -
b1100000101000 7
1"
b110000010100000000000000 6
b10000000000000 %
b10000000000000 )
b10000000000000 5
b10000000000000 #
#180
0"
#190
b110100101000011 +
b110100101000011 ?
b1000001010000 ,
b1000001010000 ;
b11010010100001100001101010 >
b1000101101110001 3
b1000101101110001 <
b100000101000000000000000 :
b10000000000000 2
b10000000000000 9
b100000000000 1
b1010110100010111 !
b1010110100010111 *
b11000001010 -
b11000001010 7
1"
b1100000101000000000000 6
b100000000000 %
b100000000000 )
b100000000000 5
b100000000000 #
#200
0"
#210
b1000011100111000 +
b1000011100111000 ?
b10000010100 ,
b10000010100 ;
b100001110011100010101001010 >
b1011001100100001 3
b1011001100100001 <
b1000001010000000000000 :
b100000000000 2
b100000000000 9
b1000000000000 1
b1000100011110000 !
b1000100011110000 *
b110000010100 -
b110000010100 7
1"
b11000001010000000000000 6
b1000000000000 %
b1000000000000 )
b1000000000000 5
b1000000000000 #
#220
0"
#230
b110001011010000 +
b110001011010000 ?
b100000101000 ,
b100000101000 ;
b11000101101000000011111100 >
b1000001011100110 3
b1000001011100110 <
b10000010100000000000000 :
b1000000000000 2
b1000000000000 9
b100000000000 1
b1010101101100010 !
b1010101101100010 *
b11000001010 -
b11000001010 7
1"
b1100000101000000000000 6
b100000000000 %
b100000000000 )
b100000000000 5
b100000000000 #
#240
0"
#250
b1000111100001100 +
b1000111100001100 ?
b10000010100 ,
b10000010100 ;
b100011110000110011100000000 >
b1011110110000000 3
b1011110110000000 <
b1000001010000000000000 :
b100000000000 2
b100000000000 9
b10000000000000 1
b1000110100110000 !
b1000110100110000 *
b1100000101000 -
b1100000101000 7
1"
b110000010100000000000000 6
b10000000000000 %
b10000000000000 )
b10000000000000 5
b10000000000000 #
#260
0"
#270
b101110011100111 +
b101110011100111 ?
b1000001010000 ,
b1000001010000 ;
b10111001110011101010110100 >
b111101100010010 3
b111101100010010 <
b100000101000000000000000 :
b10000000000000 2
b10000000000000 9
b100000000000 1
b1011100101110011 !
b1011100101110011 *
b11000001010 -
b11000001010 7
1"
b1100000101000000000000 6
b100000000000 %
b100000000000 )
b100000000000 5
b100000000000 #
#280
0"
#290
b1001000010001101 +
b1001000010001101 ?
b10000010100 ,
b10000010100 ;
b100100001000110100011100010 >
b1011111101111101 3
b1011111101111101 <
b1000001010000000000000 :
b100000000000 2
b100000000000 9
b1000000000000 1
b111111110011011 !
b111111110011011 *
b110000010100 -
b110000010100 7
1"
b11000001010000000000000 6
b1000000000000 %
b1000000000000 )
b1000000000000 5
b1000000000000 #
#300
0"
#310
b101101111000100 +
b101101111000100 ?
b100000101000 ,
b100000101000 ;
b10110111100010010110101010 >
b111100110010001 3
b111100110010001 <
b10000010100000000000000 :
b1000000000000 2
b1000000000000 9
b100000000000 1
b1011001001101110 !
b1011001001101110 *
b11000001010 -
b11000001010 7
1"
b1100000101000000000000 6
b100000000000 %
b100000000000 )
b100000000000 5
b100000000000 #
#320
0"
#330
b1001010001011110 +
b1001010001011110 ?
b10000010100 ,
b10000010100 ;
b100101000101111010101111000 >
b1100010010001100 3
b1100010010001100 <
b1000001010000000000000 :
b100000000000 2
b100000000000 9
b10000000000000 1
b1000011111011110 !
b1000011111011110 *
b1100000101000 -
b1100000101000 7
1"
b110000010100000000000000 6
b10000000000000 %
b10000000000000 )
b10000000000000 5
b10000000000000 #
#340
0"
#350
b101100011100011 +
b101100011100011 ?
b1000001010000 ,
b1000001010000 ;
b10110001110001100110000000 >
b111010111000000 3
b111010111000000 <
b100000101000000000000000 :
b10000000000000 2
b10000000000000 9
b100000000000 1
b1011110101110111 !
b1011110101110111 *
b11000001010 -
b11000001010 7
1"
b1100000101000000000000 6
b100000000000 %
b100000000000 )
b100000000000 5
b100000000000 #
#360
0"
#370
b1001001110010101 +
b1001001110010101 ?
b10000010100 ,
b10000010100 ;
b100100111001010100100001010 >
b1100001110000001 3
b1100001110000001 <
b1000001010000000000000 :
b100000000000 2
b100000000000 9
b1000000000000 1
b111110010010011 !
b111110010010011 *
b110000010100 -
b110000010100 7
1"
b11000001010000000000000 6
b1000000000000 %
b1000000000000 )
b1000000000000 5
b1000000000000 #
#380
0"
#390
b101100101111010 +
b101100101111010 ?
b100000101000 ,
b100000101000 ;
b10110010111101011101011010 >
b111011010001001 3
b111011010001001 <
b10000010100000000000000 :
b1000000000000 2
b1000000000000 9
b100000000000 1
b1011010010111000 !
b1011010010111000 *
b11000001010 -
b11000001010 7
1"
b1100000101000000000000 6
b100000000000 %
b100000000000 )
b100000000000 5
b100000000000 #
#400
0"
#410
b1001011000011001 +
b1001011000011001 ?
b10000010100 ,
b10000010100 ;
b100101100001100100001011100 >
b1100011011010110 3
b1100011011010110 <
b1000001010000000000000 :
b100000000000 2
b100000000000 9
b10000000000000 1
b1000011000100011 !
b1000011000100011 *
b1100000101000 -
b1100000101000 7
1"
b110000010100000000000000 6
b10000000000000 %
b10000000000000 )
b10000000000000 5
b10000000000000 #
#420
0"
#430
b101011110010100 +
b101011110010100 ?
b1000001010000 ,
b1000001010000 ;
b10101111001010011000110010 >
b111010000000101 3
b111010000000101 <
b100000101000000000000000 :
b10000000000000 2
b10000000000000 9
b100000000000 1
b1011111011000110 !
b1011111011000110 *
b11000001010 -
b11000001010 7
1"
b1100000101000000000000 6
b100000000000 %
b100000000000 )
b100000000000 5
b100000000000 #
#440
0"
#450
b1001010010010010 +
b1001010010010010 ?
b10000010100 ,
b10000010100 ;
b100101001001001000000100000 >
b1100010011010000 3
b1100010011010000 <
b1000001010000000000000 :
b100000000000 2
b100000000000 9
b1000000000000 1
b111101110010110 !
b111101110010110 *
b110000010100 -
b110000010100 7
1"
b11000001010000000000000 6
b1000000000000 %
b1000000000000 )
b1000000000000 5
b1000000000000 #
#460
0"
#470
b101100010111011 +
b101100010111011 ?
b100000101000 ,
b100000101000 ;
b10110001011101111101111000 >
b111010110001100 3
b111010110001100 <
b10000010100000000000000 :
b1000000000000 2
b1000000000000 9
b100000000000 1
b1011010101110111 !
b1011010101110111 *
b11000001010 -
b11000001010 7
1"
b1100000101000000000000 6
b100000000000 %
b100000000000 )
b100000000000 5
b100000000000 #
#480
0"
#490
b1001011010101001 +
b1001011010101001 ?
b10000010100 ,
b10000010100 ;
b100101101010100100111010010 >
b1100011110010101 3
b1100011110010101 <
b1000001010000000000000 :
b100000000000 2
b100000000000 9
b10000000000000 1
b1000010110010011 !
b1000010110010011 *
b1100000101000 -
b1100000101000 7
1"
b110000010100000000000000 6
b10000000000000 %
b10000000000000 )
b10000000000000 5
b10000000000000 #
#500
0"
#510
b101011100101000 +
b101011100101000 ?
b1000001010000 ,
b1000001010000 ;
b10101110010100000010010010 >
b111001101110101 3
b111001101110101 <
b100000101000000000000000 :
b10000000000000 2
b10000000000000 9
b100000000000 1
b1011111100110010 !
b1011111100110010 *
b11000001010 -
b11000001010 7
1"
b1100000101000000000000 6
b100000000000 %
b100000000000 )
b100000000000 5
b100000000000 #
#520
0"
#530
b1001010011100011 +
b1001010011100011 ?
b10000010100 ,
b10000010100 ;
b100101001110001110001011000 >
b1100010100111100 3
b1100010100111100 <
b1000001010000000000000 :
b100000000000 2
b100000000000 9
b1000000000000 1
b111101101000101 !
b111101101000101 *
b110000010100 -
b110000010100 7
1"
b11000001010000000000000 6
b1000000000000 %
b1000000000000 )
b1000000000000 5
b1000000000000 #
#540
0"
#550
b101100001111110 +
b101100001111110 ?
b100000101000 ,
b100000101000 ;
b10110000111111011001001110 >
b111010100111011 3
b111010100111011 <
b10000010100000000000000 :
b1000000000000 2
b1000000000000 9
b100000000000 1
b1011010110110100 !
b1011010110110100 *
b11000001010 -
b11000001010 7
1"
b1100000101000000000000 6
b100000000000 %
b100000000000 )
b100000000000 5
b100000000000 #
#560
0"
#570
b1001011011010111 +
b1001011011010111 ?
b10000010100 ,
b10000010100 ;
b100101101101011101000110100 >
b1100011111010010 3
b1100011111010010 <
b1000001010000000000000 :
b100000000000 2
b100000000000 9
b10000000000000 1
b1000010101100101 !
b1000010101100101 *
b1100000101000 -
b1100000101000 7
1"
b110000010100000000000000 6
b10000000000000 %
b10000000000000 )
b10000000000000 5
b10000000000000 #
#580
0"
#590
b101011100000101 +
b101011100000101 ?
b1000001010000 ,
b1000001010000 ;
b10101110000010101011000110 >
b111001101000111 3
b111001101000111 <
b100000101000000000000000 :
b10000000000000 2
b10000000000000 9
b100000000000 1
b1011111101010101 !
b1011111101010101 *
b11000001010 -
b11000001010 7
1"
b1100000101000000000000 6
b100000000000 %
b100000000000 )
b100000000000 5
b100000000000 #
#600
0"
#610
b1001010011111101 +
b1001010011111101 ?
b10000010100 ,
b10000010100 ;
b100101001111110111110110110 >
b1100010101011111 3
b1100010101011111 <
b1000001010000000000000 :
b100000000000 2
b100000000000 9
b1000000000000 1
b111101100101011 !
b111101100101011 *
b110000010100 -
b110000010100 7
1"
b11000001010000000000000 6
b1000000000000 %
b1000000000000 )
b1000000000000 5
b1000000000000 #
#620
0"
#630
b101100001101011 +
b101100001101011 ?
b100000101000 ,
b100000101000 ;
b10110000110101100101001010 >
b111010100100001 3
b111010100100001 <
b10000010100000000000000 :
b1000000000000 2
b1000000000000 9
b100000000000 1
b1011010111000111 !
b1011010111000111 *
b11000001010 -
b11000001010 7
1"
b1100000101000000000000 6
b100000000000 %
b100000000000 )
b100000000000 5
b100000000000 #
#640
0"
#650
b1001011011100101 +
b1001011011100101 ?
b10000010100 ,
b10000010100 ;
b100101101110010110011110010 >
b1100011111100101 3
b1100011111100101 <
b1000001010000000000000 :
b100000000000 2
b100000000000 9
b10000000000000 1
b1000010101010111 !
b1000010101010111 *
b1100000101000 -
b1100000101000 7
1"
b110000010100000000000000 6
b10000000000000 %
b10000000000000 )
b10000000000000 5
b10000000000000 #
#660
0"
#670
b101011011111010 +
b101011011111010 ?
b1000001010000 ,
b1000001010000 ;
b10101101111101011000111010 >
b111001100111001 3
b111001100111001 <
b100000101000000000000000 :
b10000000000000 2
b10000000000000 9
b100000000000 1
b1011111101100000 !
b1011111101100000 *
b11000001010 -
b11000001010 7
1"
b1100000101000000000000 6
b100000000000 %
b100000000000 )
b100000000000 5
b100000000000 #
#680
0"
#690
b1001010100000110 +
b1001010100000110 ?
b10000010100 ,
b10000010100 ;
b100101010000011001000100100 >
b1100010101101010 3
b1100010101101010 <
b1000001010000000000000 :
b100000000000 2
b100000000000 9
b1000000000000 1
b111101100100010 !
b111101100100010 *
b110000010100 -
b110000010100 7
1"
b11000001010000000000000 6
b1000000000000 %
b1000000000000 )
b1000000000000 5
b1000000000000 #
#700
0"
#710
b101100001100100 +
b101100001100100 ?
b100000101000 ,
b100000101000 ;
b10110000110010001011110000 >
b111010100011000 3
b111010100011000 <
b10000010100000000000000 :
b1000000000000 2
b1000000000000 9
b100000000000 1
b1011010111001110 !
b1011010111001110 *
b11000001010 -
b11000001010 7
1"
b1100000101000000000000 6
b100000000000 %
b100000000000 )
b100000000000 5
b100000000000 #
#720
0"
#730
b1001011011101010 +
b1001011011101010 ?
b10000010100 ,
b10000010100 ;
b100101101110101011100111000 >
b1100011111101100 3
b1100011111101100 <
b1000001010000000000000 :
b100000000000 2
b100000000000 9
b10000000000000 1
b1000010101010010 !
b1000010101010010 *
b1100000101000 -
b1100000101000 7
1"
b110000010100000000000000 6
b10000000000000 %
b10000000000000 )
b10000000000000 5
b10000000000000 #
#740
0"
#750
b101011011110111 +
b101011011110111 ?
b1000001010000 ,
b1000001010000 ;
b10101101111011100000001000 >
b111001100110100 3
b111001100110100 <
b100000101000000000000000 :
b10000000000000 2
b10000000000000 9
b100000000000 1
b1011111101100011 !
b1011111101100011 *
b11000001010 -
b11000001010 7
1"
b1100000101000000000000 6
b100000000000 %
b100000000000 )
b100000000000 5
b100000000000 #
#760
0"
#770
b1001010100001000 +
b1001010100001000 ?
b10000010100 ,
b10000010100 ;
b100101010000100010001000010 >
b1100010101101101 3
b1100010101101101 <
b1000001010000000000000 :
b100000000000 2
b100000000000 9
b1000000000000 1
b111101100100000 !
b111101100100000 *
b110000010100 -
b110000010100 7
1"
b11000001010000000000000 6
b1000000000000 %
b1000000000000 )
b1000000000000 5
b1000000000000 #
#780
0"
#790
b101100001100010 +
b101100001100010 ?
b100000101000 ,
b100000101000 ;
b10110000110001011011011100 >
b111010100010110 3
b111010100010110 <
b10000010100000000000000 :
b1000000000000 2
b1000000000000 9
b100000000000 1
b1011010111010000 !
b1011010111010000 *
b11000001010 -
b11000001010 7
1"
b1100000101000000000000 6
b100000000000 %
b100000000000 )
b100000000000 5
b100000000000 #
#800
0"
#810
b1001011011101100 +
b1001011011101100 ?
b10000010100 ,
b10000010100 ;
b100101101110110001101001100 >
b1100011111101110 3
b1100011111101110 <
b1000001010000000000000 :
b100000000000 2
b100000000000 9
b10000000000000 1
b1000010101010000 !
b1000010101010000 *
b1100000101000 -
b1100000101000 7
1"
b110000010100000000000000 6
b10000000000000 %
b10000000000000 )
b10000000000000 5
b10000000000000 #
#820
0"
#830
b101011011110101 +
b101011011110101 ?
b1000001010000 ,
b1000001010000 ;
b10101101111010101111110100 >
b111001100110010 3
b111001100110010 <
b100000101000000000000000 :
b10000000000000 2
b10000000000000 9
b100000000000 1
b1011111101100101 !
b1011111101100101 *
b11000001010 -
b11000001010 7
1"
b1100000101000000000000 6
b100000000000 %
b100000000000 )
b100000000000 5
b100000000000 #
#840
0"
#850
b1001010100001010 +
b1001010100001010 ?
b10000010100 ,
b10000010100 ;
b100101010000101000001010110 >
b1100010101101111 3
b1100010101101111 <
b1000001010000000000000 :
b100000000000 2
b100000000000 9
b1000000000000 1
b111101100011110 !
b111101100011110 *
b110000010100 -
b110000010100 7
1"
b11000001010000000000000 6
b1000000000000 %
b1000000000000 )
b1000000000000 5
b1000000000000 #
#860
0"
#870
b101100001100001 +
b101100001100001 ?
b100000101000 ,
b100000101000 ;
b10110000110000101011001000 >
b111010100010100 3
b111010100010100 <
b10000010100000000000000 :
b1000000000000 2
b1000000000000 9
b100000000000 1
b1011010111010001 !
b1011010111010001 *
b11000001010 -
b11000001010 7
1"
b1100000101000000000000 6
b100000000000 %
b100000000000 )
b100000000000 5
b100000000000 #
#880
0"
#890
b1001011011101101 +
b1001011011101101 ?
b10000010100 ,
b10000010100 ;
b100101101110110100101010110 >
b1100011111101111 3
b1100011111101111 <
b1000001010000000000000 :
b100000000000 2
b100000000000 9
b10000000000000 1
b1000010101001111 !
b1000010101001111 *
b1100000101000 -
b1100000101000 7
1"
b110000010100000000000000 6
b10000000000000 %
b10000000000000 )
b10000000000000 5
b10000000000000 #
#900
0"
#910
b101011011110100 +
b101011011110100 ?
b1000001010000 ,
b1000001010000 ;
b10101101111010010111101010 >
b111001100110001 3
b111001100110001 <
b100000101000000000000000 :
b10000000000000 2
b10000000000000 9
b100000000000 1
b1011111101100110 !
b1011111101100110 *
b11000001010 -
b11000001010 7
1"
b1100000101000000000000 6
b100000000000 %
b100000000000 )
b100000000000 5
b100000000000 #
#920
0"
#930
b1001010100001010 +
b1001010100001010 ?
b10000010100 ,
b10000010100 ;
b100101010000101011001100000 >
b1100010101110000 3
b1100010101110000 <
b1000001010000000000000 :
b100000000000 2
b100000000000 9
b1000000000000 1
b111101100011110 !
b111101100011110 *
b110000010100 -
b110000010100 7
1"
b11000001010000000000000 6
b1000000000000 %
b1000000000000 )
b1000000000000 5
b1000000000000 #
#940
0"
#950
b101100001100001 +
b101100001100001 ?
b100000101000 ,
b100000101000 ;
b10110000110000101011001000 >
b111010100010100 3
b111010100010100 <
b10000010100000000000000 :
b1000000000000 2
b1000000000000 9
b100000000000 1
b1011010111010001 !
b1011010111010001 *
b11000001010 -
b11000001010 7
1"
b1100000101000000000000 6
b100000000000 %
b100000000000 )
b100000000000 5
b100000000000 #
#960
0"
#970
b1001011011101101 +
b1001011011101101 ?
b10000010100 ,
b10000010100 ;
b100101101110110100101010110 >
b1100011111101111 3
b1100011111101111 <
b1000001010000000000000 :
b100000000000 2
b100000000000 9
b10000000000000 1
b1000010101001111 !
b1000010101001111 *
b1100000101000 -
b1100000101000 7
1"
b110000010100000000000000 6
b10000000000000 %
b10000000000000 )
b10000000000000 5
b10000000000000 #
#980
0"
#990
b101011011110100 +
b101011011110100 ?
b1000001010000 ,
b1000001010000 ;
b10101101111010010111101010 >
b111001100110001 3
b111001100110001 <
b100000101000000000000000 :
b10000000000000 2
b10000000000000 9
b100000000000 1
b1011111101100110 !
b1011111101100110 *
b11000001010 -
b11000001010 7
1"
b1100000101000000000000 6
b100000000000 %
b100000000000 )
b100000000000 5
b100000000000 #
#1000
0"
#1010
b1001010100001010 +
b1001010100001010 ?
b10000010100 ,
b10000010100 ;
b100101010000101011001100000 >
b1100010101110000 3
b1100010101110000 <
b1000001010000000000000 :
b100000000000 2
b100000000000 9
b1000000000000 1
b111101100011110 !
b111101100011110 *
b110000010100 -
b110000010100 7
1"
b11000001010000000000000 6
b1000000000000 %
b1000000000000 )
b1000000000000 5
b1000000000000 #
#1020
0"
#1030
b101100001100001 +
b101100001100001 ?
b100000101000 ,
b100000101000 ;
b10110000110000101011001000 >
b111010100010100 3
b111010100010100 <
b10000010100000000000000 :
b1000000000000 2
b1000000000000 9
b100000000000 1
b1011010111010001 !
b1011010111010001 *
b11000001010 -
b11000001010 7
1"
b1100000101000000000000 6
b100000000000 %
b100000000000 )
b100000000000 5
b100000000000 #
#1040
0"
#1050
b1001011011101101 +
b1001011011101101 ?
b10000010100 ,
b10000010100 ;
b100101101110110100101010110 >
b1100011111101111 3
b1100011111101111 <
b1000001010000000000000 :
b100000000000 2
b100000000000 9
b10000000000000 1
b1000010101001111 !
b1000010101001111 *
b1100000101000 -
b1100000101000 7
1"
b110000010100000000000000 6
b10000000000000 %
b10000000000000 )
b10000000000000 5
b10000000000000 #
#1060
0"
#1070
b101011011110100 +
b101011011110100 ?
b1000001010000 ,
b1000001010000 ;
b10101101111010010111101010 >
b111001100110001 3
b111001100110001 <
b100000101000000000000000 :
b10000000000000 2
b10000000000000 9
b100000000000 1
b1011111101100110 !
b1011111101100110 *
b11000001010 -
b11000001010 7
1"
b1100000101000000000000 6
b100000000000 %
b100000000000 )
b100000000000 5
b100000000000 #
#1080
0"
