multiplier.v
module multiplier (
    input [15:0] a,b,
    output [15:0] p
);
  wire [31:0] temp_product;
   assign temp_product = a * b;
   assign p = temp_product[26:11];
    
endmodule

IIR.v
module IIR (
    input [15:0] x,
    input reset,clk,
    output reg [15:0] y
);
reg [15:0] x1,x2,y1,t1,t2,o1,o2;
wire [15:0] p1,p2,p3;
parameter
a0 =16'b1111100111110110,
a1 =16'b0000010000010100,
b1 =16'b0000011000001010;
multiplier m1(b1,t2,p1);
multiplier m2(b1,x1,p2);
multiplier m3(y,a1,p3);
// register r1(o1,clk,reset,t2);
// register r4(t2,clk,reset,y);
// register r2(x,clk,reset,t1);
// register r3(t1,clk,reset,x1);
// assign o1=p1+p2-p3;
always @(posedge clk or negedge reset) begin
    if (!reset) begin
        y<=0;
        x1<=0;
        y1<=0;
        t1<=0;
        t2<=0;
        o1<=0;
        o2<=0;
    end
    else begin
    o1<=p1+p2;
    y<=o1-p3;
    y1<=y;
    t1<=x;
    t2<=t1;
    x1<=t2;
    end
end
endmodule

iir_tb.v
module iir_tb;
    reg [15:0] x;
    reg rst, clk;
    wire [15:0] y;
    
    IIR i1(x, rst, clk, y);
    
    // Clock generation
    initial clk = 0;
    always #10 clk = ~clk;
    
    // Read input values from file
    integer file_handle,file_output;
    reg [15:0] input_value;
    integer scan_file;
    
    initial begin
        $dumpfile("waveform.vcd");
    $dumpvars(0, iir_tb);
        // Open the input file
        file_handle = $fopen("wave.txt", "r");
        file_output = $fopen("output.txt", "w");
        
        // Reset the DUT
        rst = 1;
        x=0;
        #10 rst = 0;
        #10 rst = 1;
        // Read input values from file and apply them to the DUT
        while (!$feof(file_handle)) begin
            scan_file = $fscanf(file_handle, "%b", input_value);
            if (scan_file == 1) begin
                #20; // Wait for 5 time units
                x = input_value;
                $fdisplay (file_output,"%b",y);
                
            end
        end
        
        // Close the input file
        $fclose(file_handle);
        
        // Wait for some time and finish the simulation
        #100 $finish;
    end
    
endmodule

waveform.vcd
$date
	Sun May 12 12:48:29 2024
$end
$version
	Icarus Verilog
$end
$timescale
	1s
$end
$scope module iir_tb $end
$var wire 16 ! y [15:0] $end
$var reg 1 " clk $end
$var reg 16 # input_value [15:0] $end
$var reg 1 $ rst $end
$var reg 16 % x [15:0] $end
$var integer 32 & file_handle [31:0] $end
$var integer 32 ' file_output [31:0] $end
$var integer 32 ( scan_file [31:0] $end
$scope module i1 $end
$var wire 1 " clk $end
$var wire 1 $ reset $end
$var wire 16 ) x [15:0] $end
$var wire 16 * p3 [15:0] $end
$var wire 16 + p2 [15:0] $end
$var wire 16 , p1 [15:0] $end
$var parameter 16 - a0 $end
$var parameter 16 . a1 $end
$var parameter 16 / b1 $end
$var reg 16 0 o1 [15:0] $end
$var reg 16 1 o2 [15:0] $end
$var reg 16 2 t1 [15:0] $end
$var reg 16 3 t2 [15:0] $end
$var reg 16 4 x1 [15:0] $end
$var reg 16 5 y [15:0] $end
$var reg 16 6 y1 [15:0] $end
$scope module m1 $end
$var wire 16 7 a [15:0] $end
$var wire 16 8 b [15:0] $end
$var wire 32 9 temp_product [31:0] $end
$var wire 16 : p [15:0] $end
$upscope $end
$scope module m2 $end
$var wire 16 ; a [15:0] $end
$var wire 16 < b [15:0] $end
$var wire 32 = temp_product [31:0] $end
$var wire 16 > p [15:0] $end
$upscope $end
$scope module m3 $end
$var wire 16 ? a [15:0] $end
$var wire 16 @ b [15:0] $end
$var wire 32 A temp_product [31:0] $end
$var wire 16 B p [15:0] $end
$upscope $end
$upscope $end
$upscope $end
$enddefinitions $end
$comment Show the parameter values. $end
$dumpall
b11000001010 /
b10000010100 .
b1111100111110110 -
$end
#0
$dumpvars
bx B
bx A
b10000010100 @
bx ?
bx >
bx =
bx <
b11000001010 ;
bx :
bx 9
bx 8
b11000001010 7
bx 6
bx 5
bx 4
bx 3
bx 2
bx 1
bx 0
bx ,
bx +
bx *
b0 )
bx (
b10000000000000000000000000000100 '
b10000000000000000000000000000011 &
b0 %
1$
bx #
0"
bx !
$end
#10
b0 ,
b0 :
b0 +
b0 >
b0 *
b0 B
b0 1
b0 0
b0 9
b0 3
b0 8
b0 2
b0 6
b0 =
b0 4
b0 <
b0 A
b0 !
b0 5
b0 ?
0$
1"
#20
b1 (
b10000000000000 #
1$
0"
#30
1"
#40
0"
b100000000000 #
b10000000000000 %
b10000000000000 )
#50
b10000000000000 2
1"
#60
0"
b1000000000000 #
b100000000000 %
b100000000000 )
#70
b1100000101000 ,
b1100000101000 :
b110000010100000000000000 9
b10000000000000 3
b10000000000000 8
b100000000000 2
1"
#80
0"
b100000000000 #
b1000000000000 %
b1000000000000 )
#90
b1100000101000 +
b1100000101000 >
b11000001010 ,
b11000001010 :
b110000010100000000000000 =
b10000000000000 4
b10000000000000 <
b1100000101000000000000 9
b100000000000 3
b100000000000 8
b1000000000000 2
b1100000101000 0
1"
#100
0"
b10000000000000 #
b100000000000 %
b100000000000 )
#110
b11000001010 +
b11000001010 >
b110000010100 ,
b110000010100 :
b110001010000 *
b110001010000 B
b1100000101000000000000 =
b100000000000 4
b100000000000 <
b11000001010000000000000 9
b1000000000000 3
b1000000000000 8
b100000000000 2
b11000101000001100100000 A
b1100000101000 !
b1100000101000 5
b1100000101000 ?
b1111000110010 0
1"
#120
0"
b100000000000 #
b10000000000000 %
b10000000000000 )
#130
b110000010100 +
b110000010100 >
b11000001010 ,
b11000001010 :
b100100011101 *
b100100011101 B
b11000001010000000000000 =
b1000000000000 4
b1000000000000 <
b1100000101000000000000 9
b100000000000 3
b100000000000 8
b10000000000000 2
b1100000101000 6
b10010001110110110101000 A
b1000111100010 !
b1000111100010 5
b1000111100010 ?
b1001000011110 0
1"
#140
0"
b1000000000000 #
b100000000000 %
b100000000000 )
#150
b11000001010 +
b11000001010 >
b1100000101000 ,
b1100000101000 :
b10010010111 *
b10010010111 B
b1100000101000000000000 =
b100000000000 4
b100000000000 <
b110000010100000000000000 9
b10000000000000 3
b10000000000000 8
b100000000000 2
b1000111100010 6
b1001001011100000010100 A
b100100000001 !
b100100000001 5
b100100000001 ?
1"
#160
0"
b100000000000 #
b1000000000000 %
b1000000000000 )
#170
b1100000101000 +
b1100000101000 >
b11000001010 ,
b11000001010 :
b11011100101 *
b11011100101 B
b110000010100000000000000 =
b10000000000000 4
b10000000000000 <
b1100000101000000000000 9
b100000000000 3
b100000000000 8
b1000000000000 2
b100100000001 6
b1101110010101010001100 A
b110110000111 !
b110110000111 5
b110110000111 ?
b1111000110010 0
1"
#180
0"
b10000000000000 #
b100000000000 %
b100000000000 )
#190
b11000001010 +
b11000001010 >
b110000010100 ,
b110000010100 :
b101111100000 *
b101111100000 B
b1100000101000000000000 =
b100000000000 4
b100000000000 <
b11000001010000000000000 9
b1000000000000 3
b1000000000000 8
b100000000000 2
b110110000111 6
b10111110000011000000100 A
b1011101001101 !
b1011101001101 5
b1011101001101 ?
1"
#200
0"
b100000000000 #
b10000000000000 %
b10000000000000 )
#210
b110000010100 +
b110000010100 >
b11000001010 ,
b11000001010 :
b100101010110 *
b100101010110 B
b11000001010000000000000 =
b1000000000000 4
b1000000000000 <
b1100000101000000000000 9
b100000000000 3
b100000000000 8
b10000000000000 2
b1011101001101 6
b10010101011011001101000 A
b1001001010010 !
b1001001010010 5
b1001001010010 ?
b1001000011110 0
1"
#220
0"
b1000000000000 #
b100000000000 %
b100000000000 )
#230
b11000001010 +
b11000001010 >
b1100000101000 ,
b1100000101000 :
b10001111001 *
b10001111001 B
b1100000101000000000000 =
b100000000000 4
b100000000000 <
b110000010100000000000000 9
b10000000000000 3
b10000000000000 8
b100000000000 2
b1001001010010 6
b1000111100111110100000 A
b100011001000 !
b100011001000 5
b100011001000 ?
1"
#240
0"
b100000000000 #
b1000000000000 %
b1000000000000 )
#250
b1100000101000 +
b1100000101000 >
b11000001010 ,
b11000001010 :
b11011110100 *
b11011110100 B
b110000010100000000000000 =
b10000000000000 4
b10000000000000 <
b1100000101000000000000 9
b100000000000 3
b100000000000 8
b1000000000000 2
b100011001000 6
b1101111010010011100100 A
b110110100101 !
b110110100101 5
b110110100101 ?
b1111000110010 0
1"
#260
0"
b10000000000000 #
b100000000000 %
b100000000000 )
#270
b11000001010 +
b11000001010 >
b110000010100 ,
b110000010100 :
b101111011001 *
b101111011001 B
b1100000101000000000000 =
b100000000000 4
b100000000000 <
b11000001010000000000000 9
b1000000000000 3
b1000000000000 8
b100000000000 2
b110110100101 6
b10111101100100011011000 A
b1011100111110 !
b1011100111110 5
b1011100111110 ?
1"
#280
0"
b100000000000 #
b10000000000000 %
b10000000000000 )
#290
b110000010100 +
b110000010100 >
b11000001010 ,
b11000001010 :
b100101011010 *
b100101011010 B
b11000001010000000000000 =
b1000000000000 4
b1000000000000 <
b1100000101000000000000 9
b100000000000 3
b100000000000 8
b10000000000000 2
b1011100111110 6
b10010101101001011110100 A
b1001001011001 !
b1001001011001 5
b1001001011001 ?
b1001000011110 0
1"
#300
0"
b1000000000000 #
b100000000000 %
b100000000000 )
#310
b11000001010 +
b11000001010 >
b1100000101000 ,
b1100000101000 :
b10001110111 *
b10001110111 B
b1100000101000000000000 =
b100000000000 4
b100000000000 <
b110000010100000000000000 9
b10000000000000 3
b10000000000000 8
b100000000000 2
b1001001011001 6
b1000111011111101010000 A
b100011000100 !
b100011000100 5
b100011000100 ?
1"
#320
0"
b100000000000 #
b1000000000000 %
b1000000000000 )
#330
b1100000101000 +
b1100000101000 >
b11000001010 ,
b11000001010 :
b11011110101 *
b11011110101 B
b110000010100000000000000 =
b10000000000000 4
b10000000000000 <
b1100000101000000000000 9
b100000000000 3
b100000000000 8
b1000000000000 2
b100011000100 6
b1101111010110100001100 A
b110110100111 !
b110110100111 5
b110110100111 ?
b1111000110010 0
1"
#340
0"
b10000000000000 #
b100000000000 %
b100000000000 )
#350
b11000001010 +
b11000001010 >
b110000010100 ,
b110000010100 :
b101111011000 *
b101111011000 B
b1100000101000000000000 =
b100000000000 4
b100000000000 <
b11000001010000000000000 9
b1000000000000 3
b1000000000000 8
b100000000000 2
b110110100111 6
b10111101100010011000100 A
b1011100111101 !
b1011100111101 5
b1011100111101 ?
1"
#360
0"
b100000000000 #
b10000000000000 %
b10000000000000 )
#370
b110000010100 +
b110000010100 >
b11000001010 ,
b11000001010 :
b100101011010 *
b100101011010 B
b11000001010000000000000 =
b1000000000000 4
b1000000000000 <
b1100000101000000000000 9
b100000000000 3
b100000000000 8
b10000000000000 2
b1011100111101 6
b10010101101011100001000 A
b1001001011010 !
b1001001011010 5
b1001001011010 ?
b1001000011110 0
1"
#380
0"
b1000000000000 #
b100000000000 %
b100000000000 )
#390
b11000001010 +
b11000001010 >
b1100000101000 ,
b1100000101000 :
b10001110111 *
b10001110111 B
b1100000101000000000000 =
b100000000000 4
b100000000000 <
b110000010100000000000000 9
b10000000000000 3
b10000000000000 8
b100000000000 2
b1001001011010 6
b1000111011111101010000 A
b100011000100 !
b100011000100 5
b100011000100 ?
1"
#400
0"
b100000000000 #
b1000000000000 %
b1000000000000 )
#410
b1100000101000 +
b1100000101000 >
b11000001010 ,
b11000001010 :
b11011110101 *
b11011110101 B
b110000010100000000000000 =
b10000000000000 4
b10000000000000 <
b1100000101000000000000 9
b100000000000 3
b100000000000 8
b1000000000000 2
b100011000100 6
b1101111010110100001100 A
b110110100111 !
b110110100111 5
b110110100111 ?
b1111000110010 0
1"
#420
0"
b10000000000000 #
b100000000000 %
b100000000000 )
#430
b11000001010 +
b11000001010 >
b110000010100 ,
b110000010100 :
b101111011000 *
b101111011000 B
b1100000101000000000000 =
b100000000000 4
b100000000000 <
b11000001010000000000000 9
b1000000000000 3
b1000000000000 8
b100000000000 2
b110110100111 6
b10111101100010011000100 A
b1011100111101 !
b1011100111101 5
b1011100111101 ?
1"
#440
0"
b100000000000 #
b10000000000000 %
b10000000000000 )
#450
b110000010100 +
b110000010100 >
b11000001010 ,
b11000001010 :
b100101011010 *
b100101011010 B
b11000001010000000000000 =
b1000000000000 4
b1000000000000 <
b1100000101000000000000 9
b100000000000 3
b100000000000 8
b10000000000000 2
b1011100111101 6
b10010101101011100001000 A
b1001001011010 !
b1001001011010 5
b1001001011010 ?
b1001000011110 0
1"
#460
0"
b1000000000000 #
b100000000000 %
b100000000000 )
#470
b11000001010 +
b11000001010 >
b1100000101000 ,
b1100000101000 :
b10001110111 *
b10001110111 B
b1100000101000000000000 =
b100000000000 4
b100000000000 <
b110000010100000000000000 9
b10000000000000 3
b10000000000000 8
b100000000000 2
b1001001011010 6
b1000111011111101010000 A
b100011000100 !
b100011000100 5
b100011000100 ?
1"
#480
0"
b100000000000 #
b1000000000000 %
b1000000000000 )
#490
b1100000101000 +
b1100000101000 >
b11000001010 ,
b11000001010 :
b11011110101 *
b11011110101 B
b110000010100000000000000 =
b10000000000000 4
b10000000000000 <
b1100000101000000000000 9
b100000000000 3
b100000000000 8
b1000000000000 2
b100011000100 6
b1101111010110100001100 A
b110110100111 !
b110110100111 5
b110110100111 ?
b1111000110010 0
1"
#500
0"
b10000000000000 #
b100000000000 %
b100000000000 )
#510
b11000001010 +
b11000001010 >
b110000010100 ,
b110000010100 :
b101111011000 *
b101111011000 B
b1100000101000000000000 =
b100000000000 4
b100000000000 <
b11000001010000000000000 9
b1000000000000 3
b1000000000000 8
b100000000000 2
b110110100111 6
b10111101100010011000100 A
b1011100111101 !
b1011100111101 5
b1011100111101 ?
1"
#520
0"
b100000000000 #
b10000000000000 %
b10000000000000 )
#530
b110000010100 +
b110000010100 >
b11000001010 ,
b11000001010 :
b100101011010 *
b100101011010 B
b11000001010000000000000 =
b1000000000000 4
b1000000000000 <
b1100000101000000000000 9
b100000000000 3
b100000000000 8
b10000000000000 2
b1011100111101 6
b10010101101011100001000 A
b1001001011010 !
b1001001011010 5
b1001001011010 ?
b1001000011110 0
1"
#540
0"
b1000000000000 #
b100000000000 %
b100000000000 )
#550
b11000001010 +
b11000001010 >
b1100000101000 ,
b1100000101000 :
b10001110111 *
b10001110111 B
b1100000101000000000000 =
b100000000000 4
b100000000000 <
b110000010100000000000000 9
b10000000000000 3
b10000000000000 8
b100000000000 2
b1001001011010 6
b1000111011111101010000 A
b100011000100 !
b100011000100 5
b100011000100 ?
1"
#560
0"
b100000000000 #
b1000000000000 %
b1000000000000 )
#570
b1100000101000 +
b1100000101000 >
b11000001010 ,
b11000001010 :
b11011110101 *
b11011110101 B
b110000010100000000000000 =
b10000000000000 4
b10000000000000 <
b1100000101000000000000 9
b100000000000 3
b100000000000 8
b1000000000000 2
b100011000100 6
b1101111010110100001100 A
b110110100111 !
b110110100111 5
b110110100111 ?
b1111000110010 0
1"
#580
0"
b10000000000000 #
b100000000000 %
b100000000000 )
#590
b11000001010 +
b11000001010 >
b110000010100 ,
b110000010100 :
b101111011000 *
b101111011000 B
b1100000101000000000000 =
b100000000000 4
b100000000000 <
b11000001010000000000000 9
b1000000000000 3
b1000000000000 8
b100000000000 2
b110110100111 6
b10111101100010011000100 A
b1011100111101 !
b1011100111101 5
b1011100111101 ?
1"
#600
0"
b100000000000 #
b10000000000000 %
b10000000000000 )
#610
b110000010100 +
b110000010100 >
b11000001010 ,
b11000001010 :
b100101011010 *
b100101011010 B
b11000001010000000000000 =
b1000000000000 4
b1000000000000 <
b1100000101000000000000 9
b100000000000 3
b100000000000 8
b10000000000000 2
b1011100111101 6
b10010101101011100001000 A
b1001001011010 !
b1001001011010 5
b1001001011010 ?
b1001000011110 0
1"
#620
0"
b1000000000000 #
b100000000000 %
b100000000000 )
#630
b11000001010 +
b11000001010 >
b1100000101000 ,
b1100000101000 :
b10001110111 *
b10001110111 B
b1100000101000000000000 =
b100000000000 4
b100000000000 <
b110000010100000000000000 9
b10000000000000 3
b10000000000000 8
b100000000000 2
b1001001011010 6
b1000111011111101010000 A
b100011000100 !
b100011000100 5
b100011000100 ?
1"
#640
0"
b100000000000 #
b1000000000000 %
b1000000000000 )
#650
b1100000101000 +
b1100000101000 >
b11000001010 ,
b11000001010 :
b11011110101 *
b11011110101 B
b110000010100000000000000 =
b10000000000000 4
b10000000000000 <
b1100000101000000000000 9
b100000000000 3
b100000000000 8
b1000000000000 2
b100011000100 6
b1101111010110100001100 A
b110110100111 !
b110110100111 5
b110110100111 ?
b1111000110010 0
1"
#660
0"
b10000000000000 #
b100000000000 %
b100000000000 )
#670
b11000001010 +
b11000001010 >
b110000010100 ,
b110000010100 :
b101111011000 *
b101111011000 B
b1100000101000000000000 =
b100000000000 4
b100000000000 <
b11000001010000000000000 9
b1000000000000 3
b1000000000000 8
b100000000000 2
b110110100111 6
b10111101100010011000100 A
b1011100111101 !
b1011100111101 5
b1011100111101 ?
1"
#680
0"
b100000000000 #
b10000000000000 %
b10000000000000 )
#690
b110000010100 +
b110000010100 >
b11000001010 ,
b11000001010 :
b100101011010 *
b100101011010 B
b11000001010000000000000 =
b1000000000000 4
b1000000000000 <
b1100000101000000000000 9
b100000000000 3
b100000000000 8
b10000000000000 2
b1011100111101 6
b10010101101011100001000 A
b1001001011010 !
b1001001011010 5
b1001001011010 ?
b1001000011110 0
1"
#700
0"
b1000000000000 #
b100000000000 %
b100000000000 )
#710
b11000001010 +
b11000001010 >
b1100000101000 ,
b1100000101000 :
b10001110111 *
b10001110111 B
b1100000101000000000000 =
b100000000000 4
b100000000000 <
b110000010100000000000000 9
b10000000000000 3
b10000000000000 8
b100000000000 2
b1001001011010 6
b1000111011111101010000 A
b100011000100 !
b100011000100 5
b100011000100 ?
1"
#720
0"
b100000000000 #
b1000000000000 %
b1000000000000 )
#730
b1100000101000 +
b1100000101000 >
b11000001010 ,
b11000001010 :
b11011110101 *
b11011110101 B
b110000010100000000000000 =
b10000000000000 4
b10000000000000 <
b1100000101000000000000 9
b100000000000 3
b100000000000 8
b1000000000000 2
b100011000100 6
b1101111010110100001100 A
b110110100111 !
b110110100111 5
b110110100111 ?
b1111000110010 0
1"
#740
0"
b10000000000000 #
b100000000000 %
b100000000000 )
#750
b11000001010 +
b11000001010 >
b110000010100 ,
b110000010100 :
b101111011000 *
b101111011000 B
b1100000101000000000000 =
b100000000000 4
b100000000000 <
b11000001010000000000000 9
b1000000000000 3
b1000000000000 8
b100000000000 2
b110110100111 6
b10111101100010011000100 A
b1011100111101 !
b1011100111101 5
b1011100111101 ?
1"
#760
0"
b100000000000 #
b10000000000000 %
b10000000000000 )
#770
b110000010100 +
b110000010100 >
b11000001010 ,
b11000001010 :
b100101011010 *
b100101011010 B
b11000001010000000000000 =
b1000000000000 4
b1000000000000 <
b1100000101000000000000 9
b100000000000 3
b100000000000 8
b10000000000000 2
b1011100111101 6
b10010101101011100001000 A
b1001001011010 !
b1001001011010 5
b1001001011010 ?
b1001000011110 0
1"
#780
0"
b1000000000000 #
b100000000000 %
b100000000000 )
#790
b11000001010 +
b11000001010 >
b1100000101000 ,
b1100000101000 :
b10001110111 *
b10001110111 B
b1100000101000000000000 =
b100000000000 4
b100000000000 <
b110000010100000000000000 9
b10000000000000 3
b10000000000000 8
b100000000000 2
b1001001011010 6
b1000111011111101010000 A
b100011000100 !
b100011000100 5
b100011000100 ?
1"
#800
0"
b100000000000 #
b1000000000000 %
b1000000000000 )
#810
b1100000101000 +
b1100000101000 >
b11000001010 ,
b11000001010 :
b11011110101 *
b11011110101 B
b110000010100000000000000 =
b10000000000000 4
b10000000000000 <
b1100000101000000000000 9
b100000000000 3
b100000000000 8
b1000000000000 2
b100011000100 6
b1101111010110100001100 A
b110110100111 !
b110110100111 5
b110110100111 ?
b1111000110010 0
1"
#820
0"
b10000000000000 #
b100000000000 %
b100000000000 )
#830
b11000001010 +
b11000001010 >
b110000010100 ,
b110000010100 :
b101111011000 *
b101111011000 B
b1100000101000000000000 =
b100000000000 4
b100000000000 <
b11000001010000000000000 9
b1000000000000 3
b1000000000000 8
b100000000000 2
b110110100111 6
b10111101100010011000100 A
b1011100111101 !
b1011100111101 5
b1011100111101 ?
1"
#840
0"
b100000000000 #
b10000000000000 %
b10000000000000 )
#850
b110000010100 +
b110000010100 >
b11000001010 ,
b11000001010 :
b100101011010 *
b100101011010 B
b11000001010000000000000 =
b1000000000000 4
b1000000000000 <
b1100000101000000000000 9
b100000000000 3
b100000000000 8
b10000000000000 2
b1011100111101 6
b10010101101011100001000 A
b1001001011010 !
b1001001011010 5
b1001001011010 ?
b1001000011110 0
1"
#860
0"
b1000000000000 #
b100000000000 %
b100000000000 )
#870
b11000001010 +
b11000001010 >
b1100000101000 ,
b1100000101000 :
b10001110111 *
b10001110111 B
b1100000101000000000000 =
b100000000000 4
b100000000000 <
b110000010100000000000000 9
b10000000000000 3
b10000000000000 8
b100000000000 2
b1001001011010 6
b1000111011111101010000 A
b100011000100 !
b100011000100 5
b100011000100 ?
1"
#880
0"
b100000000000 #
b1000000000000 %
b1000000000000 )
#890
b1100000101000 +
b1100000101000 >
b11000001010 ,
b11000001010 :
b11011110101 *
b11011110101 B
b110000010100000000000000 =
b10000000000000 4
b10000000000000 <
b1100000101000000000000 9
b100000000000 3
b100000000000 8
b1000000000000 2
b100011000100 6
b1101111010110100001100 A
b110110100111 !
b110110100111 5
b110110100111 ?
b1111000110010 0
1"
#900
0"
b10000000000000 #
b100000000000 %
b100000000000 )
#910
b11000001010 +
b11000001010 >
b110000010100 ,
b110000010100 :
b101111011000 *
b101111011000 B
b1100000101000000000000 =
b100000000000 4
b100000000000 <
b11000001010000000000000 9
b1000000000000 3
b1000000000000 8
b100000000000 2
b110110100111 6
b10111101100010011000100 A
b1011100111101 !
b1011100111101 5
b1011100111101 ?
1"
#920
0"
b100000000000 #
b10000000000000 %
b10000000000000 )
#930
b110000010100 +
b110000010100 >
b11000001010 ,
b11000001010 :
b100101011010 *
b100101011010 B
b11000001010000000000000 =
b1000000000000 4
b1000000000000 <
b1100000101000000000000 9
b100000000000 3
b100000000000 8
b10000000000000 2
b1011100111101 6
b10010101101011100001000 A
b1001001011010 !
b1001001011010 5
b1001001011010 ?
b1001000011110 0
1"
#940
0"
b1000000000000 #
b100000000000 %
b100000000000 )
#950
b11000001010 +
b11000001010 >
b1100000101000 ,
b1100000101000 :
b10001110111 *
b10001110111 B
b1100000101000000000000 =
b100000000000 4
b100000000000 <
b110000010100000000000000 9
b10000000000000 3
b10000000000000 8
b100000000000 2
b1001001011010 6
b1000111011111101010000 A
b100011000100 !
b100011000100 5
b100011000100 ?
1"
#960
0"
b100000000000 #
b1000000000000 %
b1000000000000 )
#970
b1100000101000 +
b1100000101000 >
b11000001010 ,
b11000001010 :
b11011110101 *
b11011110101 B
b110000010100000000000000 =
b10000000000000 4
b10000000000000 <
b1100000101000000000000 9
b100000000000 3
b100000000000 8
b1000000000000 2
b100011000100 6
b1101111010110100001100 A
b110110100111 !
b110110100111 5
b110110100111 ?
b1111000110010 0
1"
#980
0"
b10000000000000 #
b100000000000 %
b100000000000 )
#990
b11000001010 +
b11000001010 >
b110000010100 ,
b110000010100 :
b101111011000 *
b101111011000 B
b1100000101000000000000 =
b100000000000 4
b100000000000 <
b11000001010000000000000 9
b1000000000000 3
b1000000000000 8
b100000000000 2
b110110100111 6
b10111101100010011000100 A
b1011100111101 !
b1011100111101 5
b1011100111101 ?
1"
#1000
0"
b100000000000 #
b10000000000000 %
b10000000000000 )
#1010
b110000010100 +
b110000010100 >
b11000001010 ,
b11000001010 :
b100101011010 *
b100101011010 B
b11000001010000000000000 =
b1000000000000 4
b1000000000000 <
b1100000101000000000000 9
b100000000000 3
b100000000000 8
b10000000000000 2
b1011100111101 6
b10010101101011100001000 A
b1001001011010 !
b1001001011010 5
b1001001011010 ?
b1001000011110 0
1"
#1020
0"
b1000000000000 #
b100000000000 %
b100000000000 )
#1030
b11000001010 +
b11000001010 >
b1100000101000 ,
b1100000101000 :
b10001110111 *
b10001110111 B
b1100000101000000000000 =
b100000000000 4
b100000000000 <
b110000010100000000000000 9
b10000000000000 3
b10000000000000 8
b100000000000 2
b1001001011010 6
b1000111011111101010000 A
b100011000100 !
b100011000100 5
b100011000100 ?
1"
#1040
0"
b100000000000 #
b1000000000000 %
b1000000000000 )
#1050
b1100000101000 +
b1100000101000 >
b11000001010 ,
b11000001010 :
b11011110101 *
b11011110101 B
b110000010100000000000000 =
b10000000000000 4
b10000000000000 <
b1100000101000000000000 9
b100000000000 3
b100000000000 8
b1000000000000 2
b100011000100 6
b1101111010110100001100 A
b110110100111 !
b110110100111 5
b110110100111 ?
b1111000110010 0
1"
#1060
0"
b10000000000000 #
b100000000000 %
b100000000000 )
#1070
b11000001010 +
b11000001010 >
b110000010100 ,
b110000010100 :
b101111011000 *
b101111011000 B
b1100000101000000000000 =
b100000000000 4
b100000000000 <
b11000001010000000000000 9
b1000000000000 3
b1000000000000 8
b100000000000 2
b110110100111 6
b10111101100010011000100 A
b1011100111101 !
b1011100111101 5
b1011100111101 ?
1"
#1080
0"
b100000000000 #
b10000000000000 %
b10000000000000 )
#1090
b110000010100 +
b110000010100 >
b11000001010 ,
b11000001010 :
b100101011010 *
b100101011010 B
b11000001010000000000000 =
b1000000000000 4
b1000000000000 <
b1100000101000000000000 9
b100000000000 3
b100000000000 8
b10000000000000 2
b1011100111101 6
b10010101101011100001000 A
b1001001011010 !
b1001001011010 5
b1001001011010 ?
b1001000011110 0
1"
#1100
0"
b1000000000000 #
b100000000000 %
b100000000000 )
#1110
b11000001010 +
b11000001010 >
b1100000101000 ,
b1100000101000 :
b10001110111 *
b10001110111 B
b1100000101000000000000 =
b100000000000 4
b100000000000 <
b110000010100000000000000 9
b10000000000000 3
b10000000000000 8
b100000000000 2
b1001001011010 6
b1000111011111101010000 A
b100011000100 !
b100011000100 5
b100011000100 ?
1"
#1120
0"
b100000000000 #
b1000000000000 %
b1000000000000 )
#1130
b1100000101000 +
b1100000101000 >
b11000001010 ,
b11000001010 :
b11011110101 *
b11011110101 B
b110000010100000000000000 =
b10000000000000 4
b10000000000000 <
b1100000101000000000000 9
b100000000000 3
b100000000000 8
b1000000000000 2
b100011000100 6
b1101111010110100001100 A
b110110100111 !
b110110100111 5
b110110100111 ?
b1111000110010 0
1"
#1140
0"
b10000000000000 #
b100000000000 %
b100000000000 )
#1150
b11000001010 +
b11000001010 >
b110000010100 ,
b110000010100 :
b101111011000 *
b101111011000 B
b1100000101000000000000 =
b100000000000 4
b100000000000 <
b11000001010000000000000 9
b1000000000000 3
b1000000000000 8
b100000000000 2
b110110100111 6
b10111101100010011000100 A
b1011100111101 !
b1011100111101 5
b1011100111101 ?
1"
#1160
0"
b100000000000 #
b10000000000000 %
b10000000000000 )
#1170
b110000010100 +
b110000010100 >
b11000001010 ,
b11000001010 :
b100101011010 *
b100101011010 B
b11000001010000000000000 =
b1000000000000 4
b1000000000000 <
b1100000101000000000000 9
b100000000000 3
b100000000000 8
b10000000000000 2
b1011100111101 6
b10010101101011100001000 A
b1001001011010 !
b1001001011010 5
b1001001011010 ?
b1001000011110 0
1"
#1180
0"
b1000000000000 #
b100000000000 %
b100000000000 )
#1190
b11000001010 +
b11000001010 >
b1100000101000 ,
b1100000101000 :
b10001110111 *
b10001110111 B
b1100000101000000000000 =
b100000000000 4
b100000000000 <
b110000010100000000000000 9
b10000000000000 3
b10000000000000 8
b100000000000 2
b1001001011010 6
b1000111011111101010000 A
b100011000100 !
b100011000100 5
b100011000100 ?
1"
#1200
0"
b100000000000 #
b1000000000000 %
b1000000000000 )
#1210
b1100000101000 +
b1100000101000 >
b11000001010 ,
b11000001010 :
b11011110101 *
b11011110101 B
b110000010100000000000000 =
b10000000000000 4
b10000000000000 <
b1100000101000000000000 9
b100000000000 3
b100000000000 8
b1000000000000 2
b100011000100 6
b1101111010110100001100 A
b110110100111 !
b110110100111 5
b110110100111 ?
b1111000110010 0
1"
#1220
0"
b10000000000000 #
b100000000000 %
b100000000000 )
#1230
b11000001010 +
b11000001010 >
b110000010100 ,
b110000010100 :
b101111011000 *
b101111011000 B
b1100000101000000000000 =
b100000000000 4
b100000000000 <
b11000001010000000000000 9
b1000000000000 3
b1000000000000 8
b100000000000 2
b110110100111 6
b10111101100010011000100 A
b1011100111101 !
b1011100111101 5
b1011100111101 ?
1"
#1240
0"
b100000000000 #
b10000000000000 %
b10000000000000 )
#1250
b110000010100 +
b110000010100 >
b11000001010 ,
b11000001010 :
b100101011010 *
b100101011010 B
b11000001010000000000000 =
b1000000000000 4
b1000000000000 <
b1100000101000000000000 9
b100000000000 3
b100000000000 8
b10000000000000 2
b1011100111101 6
b10010101101011100001000 A
b1001001011010 !
b1001001011010 5
b1001001011010 ?
b1001000011110 0
1"
#1260
0"
b1000000000000 #
b100000000000 %
b100000000000 )
#1270
b11000001010 +
b11000001010 >
b1100000101000 ,
b1100000101000 :
b10001110111 *
b10001110111 B
b1100000101000000000000 =
b100000000000 4
b100000000000 <
b110000010100000000000000 9
b10000000000000 3
b10000000000000 8
b100000000000 2
b1001001011010 6
b1000111011111101010000 A
b100011000100 !
b100011000100 5
b100011000100 ?
1"
#1280
0"
b100000000000 #
b1000000000000 %
b1000000000000 )
#1290
b1100000101000 +
b1100000101000 >
b11000001010 ,
b11000001010 :
b11011110101 *
b11011110101 B
b110000010100000000000000 =
b10000000000000 4
b10000000000000 <
b1100000101000000000000 9
b100000000000 3
b100000000000 8
b1000000000000 2
b100011000100 6
b1101111010110100001100 A
b110110100111 !
b110110100111 5
b110110100111 ?
b1111000110010 0
1"
#1300
0"
b10000000000000 #
b100000000000 %
b100000000000 )
